{
	"apiVersion": 2,
	"name": "nielslange/free-shipping-progress-bar",
	"title": "Free Shipping Progress Bar",
	"description": "Show a free shipping progress bar.",
	"version": "0.1.0",
	"category": "woocommerce",
	"parent": [ "woocommerce/cart-totals-block" ],
	"supports": {
		"html": false,
		"color": {
			"__experimentalSkipSerialization": true
		}
	},
	"attributes": {
		"currentTotal": {
			"type": "string",
			"default": "15"
		},
		"freeShippingFrom": {
			"type": "string",
			"default": "50"
		},
		"labelInsufficientTotals": {
			"type": "string",
			"default": "Spend only {amount} more to get free shipping!"
		},
		"labelSufficientTotals": {
			"type": "string",
			"default": "You have qualified for free shipping. Great job!"
		}
	},
	"textdomain": "free-shipping-progress-bar",
	"editorScript": "file:./build/index.js",
	"editorStyle": "file:./build/index.css",
	"style": "file:./build/style-index.css"
}
